forfiles/__init__.py
forfiles/directory.py
forfiles/file.py
forfiles/image.py
forfiles/py.typed
forfiles-5.0.0.dist-info/METADATA
forfiles-5.0.0.dist-info/WHEEL
forfiles-5.0.0.dist-info/licenses/LICENSE
forfiles-5.0.0.dist-info/RECORD
