Metadata-Version: 2.3
Name: forfiles
Version: 5.0.0
Summary: Useful tools for files
Project-URL: Home, https://github.com/4mbl/forfiles
Project-URL: Repository, https://github.com/4mbl/forfiles
Project-URL: Documentation, https://github.com/4mbl/forfiles/blob/main/README.md
Project-URL: Bug Tracker, https://github.com/4mbl/forfiles/issues
Author: 4MBL
License: MIT License
License-File: LICENSE
Keywords: directories,files,fs,images,utility
Classifier: Development Status :: 5 - Production/Stable
Classifier: Intended Audience :: Developers
Classifier: License :: OSI Approved :: MIT License
Classifier: Natural Language :: English
Classifier: Operating System :: OS Independent
Classifier: Programming Language :: Python :: 3
Classifier: Programming Language :: Python :: 3.9
Classifier: Programming Language :: Python :: 3.10
Classifier: Programming Language :: Python :: 3.11
Classifier: Programming Language :: Python :: 3.12
Classifier: Programming Language :: Python :: 3.13
Classifier: Programming Language :: Python :: Implementation :: CPython
Classifier: Topic :: Software Development
Classifier: Topic :: Software Development :: Libraries
Classifier: Topic :: Utilities
Classifier: Typing :: Typed
Requires-Python: >=3.9
Requires-Dist: pillow<11.1.0,>=11.0.0
